admin_auto_filters/__init__.py
admin_auto_filters/apps.py
admin_auto_filters/filters.py
admin_auto_filters/py.typed
admin_auto_filters/views.py
admin_auto_filters/static/django-admin-autocomplete-filter/css/autocomplete-fix.css
admin_auto_filters/static/django-admin-autocomplete-filter/js/autocomplete_filter_qs.js
admin_auto_filters/templates/django-admin-autocomplete-filter/autocomplete-filter.html
django_admin_autocomplete_filters-0.8.0.dist-info/licenses/LICENSE
django_admin_autocomplete_filters-0.8.0.dist-info/METADATA
django_admin_autocomplete_filters-0.8.0.dist-info/WHEEL
django_admin_autocomplete_filters-0.8.0.dist-info/top_level.txt
django_admin_autocomplete_filters-0.8.0.dist-info/RECORD
