Metadata-Version: 2.4
Name: django-admin-autocomplete-filters
Version: 0.8.0
Summary: Render admin list filters with Django's autocomplete widget
Author-email: Filipp Balakin <filipp@balakin.ru>
Maintainer-email: Filipp Balakin <filipp@balakin.ru>
License-Expression: LGPL-3.0-or-later
Project-URL: Homepage, https://github.com/Barsoomx/django-admin-autocomplete-filters
Project-URL: Repository, https://github.com/Barsoomx/django-admin-autocomplete-filters
Project-URL: Changelog, https://github.com/Barsoomx/django-admin-autocomplete-filters/blob/main/CHANGELOG.md
Project-URL: Issues, https://github.com/Barsoomx/django-admin-autocomplete-filters/issues
Classifier: Framework :: Django
Classifier: Framework :: Django :: 4.2
Classifier: Framework :: Django :: 5.0
Classifier: Framework :: Django :: 5.1
Classifier: Framework :: Django :: 5.2
Classifier: Intended Audience :: Developers
Classifier: Operating System :: OS Independent
Classifier: Programming Language :: Python :: 3
Classifier: Programming Language :: Python :: 3.10
Classifier: Programming Language :: Python :: 3.11
Classifier: Programming Language :: Python :: 3.12
Classifier: Topic :: Internet :: WWW/HTTP
Classifier: Topic :: Software Development :: Libraries :: Python Modules
Requires-Python: >=3.10
License-File: LICENSE
Requires-Dist: Django<5.3,>=4.2
Provides-Extra: dev
Requires-Dist: ruff==0.11.7; extra == "dev"
Requires-Dist: django-stubs>=5.0.0; extra == "dev"
Requires-Dist: django-stubs-ext>=5.0.0; extra == "dev"
Requires-Dist: mypy>=1.8; extra == "dev"
Dynamic: license-file
